fishratio/README.md
fishratio/__inint__.py
fishratio/fishratio.py
fishratio/examples/input.xlsx
fishratio/examples/output.xlsx
fishratio-1.1.3.data/data/README.md
fishratio-1.1.3.dist-info/METADATA
fishratio-1.1.3.dist-info/WHEEL
fishratio-1.1.3.dist-info/entry_points.txt
fishratio-1.1.3.dist-info/top_level.txt
fishratio-1.1.3.dist-info/RECORD
