Metadata-Version: 2.1
Name: fishratio
Version: 1.1.3
Summary: Calculate the ratio and logarithmic value of species contained in several genus of a family to all species in this family.
Home-page: https://github.com/benben-miao/FishRatio
Author: benben-miao
Author-email: benben.miao@outlook.com
Maintainer: benben-miao
Maintainer-email: benben.miao@outlook.com
License: MIT License
Download-URL: https://pypi.org/project/fishratio
Keywords: CLI,Biology,Statistics
Platform: any
Classifier: Programming Language :: Python :: 3
Classifier: Operating System :: OS Independent
Requires-Dist: pandas
Requires-Dist: numpy
Requires-Dist: openpyxl
Requires-Dist: xlrd
